{
  "teacher": "Asjad Jawed",
  "no_of_students": 7,
  "no_of_bad_students": null,
  "name_of_students": ["hajra", "hasan", "ubaid"],
  "details_of_students": [
    {
      "name": "Hajra",
      "job": "DevOps Engineer",
      "skills": ["linux", "python"]
    },
    {
      "name": "Hasan",
      "job": "Senior Software Engineer",
      "bugs": null
    },
    {
      "name": "ubaid",
      "job": "CEO",
      "company_detail": {
        "name": "Exxon",
        "no_of_employees": 40
      }
    },
    {
      "name": "Amna",
      "job": "manager",
      "supervisor": ["mickey", "mouse"]
    },
    {
      "name": "usman",
      "job": "QA",
      "experience": 80
    }
  ]
}
